user_agent_scraper/__init__.py
user_agent_scraper/user_agent_scraper.py
user_agent_scraper-1.0.1.dist-info/LICENSE
user_agent_scraper-1.0.1.dist-info/METADATA
user_agent_scraper-1.0.1.dist-info/WHEEL
user_agent_scraper-1.0.1.dist-info/top_level.txt
user_agent_scraper-1.0.1.dist-info/RECORD
