Metadata-Version: 2.1
Name: user-agent-scraper
Version: 1.0.1
Summary: scrape user agents
Home-page: https://github.com/sheepsushis/user_agent_scraper
Author: sheepsushis
Author-email: gmajosi1@gmail.com
License: UNKNOWN
Platform: UNKNOWN
Requires-Python: >=3.6
License-File: LICENSE
